astmareq/__init__.py
astmareq-1.0.dist-info/METADATA
astmareq-1.0.dist-info/WHEEL
astmareq-1.0.dist-info/top_level.txt
astmareq-1.0.dist-info/RECORD
