Metadata-Version: 2.1
Name: astmareq
Version: 1.0
Summary: package with iot codes
Author: Black_shark
